<?xml version="1.0" encoding="UTF-8"?><Workbook xmlns="urn:schemas-microsoft-com:office:spreadsheet" xmlns:html="http://www.w3.org/TR/REC-html40" xmlns:o="urn:schemas-microsoft-com:office:office" xmlns:ss="urn:schemas-microsoft-com:office:spreadsheet" xmlns:x="urn:schemas-microsoft-com:office:excel"><DocumentProperties xmlns="urn:schemas-microsoft-com:office:office"><Author>ShapeChange</Author></DocumentProperties><Styles><Style ss:ID="Default" ss:Name="Normal"><Alignment/><Borders/><Font/><Interior/><NumberFormat/><Protection/></Style><Style ss:ID="s0"><Alignment ss:Horizontal="Center" ss:Vertical="Top" ss:WrapText="1"/><Font ss:Size="8.0"/></Style><Style ss:ID="s1"><Alignment ss:Horizontal="Center" ss:Vertical="Top" ss:WrapText="1"/><Font ss:Size="8.0"/><Interior ss:Color="#FCF305" ss:Pattern="Solid"/></Style><Style ss:ID="s2"><Alignment ss:Horizontal="Center" ss:Vertical="Top" ss:WrapText="1"/><Borders><Border ss:LineStyle="Continuous" ss:Position="Bottom" ss:Weight="2"/><Border ss:LineStyle="Continuous" ss:Position="Left" ss:Weight="2"/><Border ss:LineStyle="Continuous" ss:Position="Right" ss:Weight="2"/><Border ss:LineStyle="Continuous" ss:Position="Top" ss:Weight="2"/></Borders><Font ss:Bold="1" ss:Size="12.0"/><Interior ss:Color="#99CCFF" ss:Pattern="Solid"/></Style><Style ss:ID="s3"><Alignment ss:Horizontal="Center" ss:Vertical="Top" ss:WrapText="1"/><Borders><Border ss:LineStyle="Continuous" ss:Position="Bottom" ss:Weight="2"/><Border ss:LineStyle="Continuous" ss:Position="Left" ss:Weight="1"/><Border ss:LineStyle="Continuous" ss:Position="Right" ss:Weight="1"/><Border ss:LineStyle="Continuous" ss:Position="Top" ss:Weight="2"/></Borders><Font ss:Bold="1" ss:Size="11.0"/><Interior ss:Color="#B0B0B0" ss:Pattern="Solid"/></Style><Style ss:ID="s4"><Alignment ss:Horizontal="Left" ss:Vertical="Top" ss:WrapText="1"/><Borders><Border ss:LineStyle="Continuous" ss:Position="Bottom" ss:Weight="1"/><Border ss:LineStyle="Continuous" ss:Position="Left" ss:Weight="1"/><Border ss:LineStyle="Continuous" ss:Position="Right" ss:Weight="1"/><Border ss:LineStyle="Continuous" ss:Position="Top" ss:Weight="1"/></Borders><Font ss:Bold="1" ss:Size="10.0"/></Style><Style ss:ID="s41"><Alignment ss:Horizontal="Left" ss:Vertical="Top" ss:WrapText="1"/><Borders><Border ss:LineStyle="Continuous" ss:Position="Bottom" ss:Weight="1"/><Border ss:LineStyle="Continuous" ss:Position="Left" ss:Weight="1"/><Border ss:LineStyle="Continuous" ss:Position="Right" ss:Weight="1"/><Border ss:LineStyle="Continuous" ss:Position="Top" ss:Weight="1"/></Borders><Font ss:Bold="1" ss:Color="#0000FF" ss:Size="10.0"/></Style><Style ss:ID="s42"><Alignment ss:Horizontal="Left" ss:Vertical="Top" ss:WrapText="1"/><Borders><Border ss:LineStyle="Continuous" ss:Position="Bottom" ss:Weight="1"/><Border ss:LineStyle="Continuous" ss:Position="Left" ss:Weight="1"/><Border ss:LineStyle="Continuous" ss:Position="Right" ss:Weight="1"/><Border ss:LineStyle="Continuous" ss:Position="Top" ss:Weight="1"/></Borders><Font ss:Bold="1" ss:Color="#008080" ss:Size="10.0"/></Style><Style ss:ID="s5"><Alignment ss:Horizontal="Left" ss:Vertical="Top" ss:WrapText="1"/><Borders><Border ss:LineStyle="Continuous" ss:Position="Bottom" ss:Weight="1"/><Border ss:LineStyle="Continuous" ss:Position="Left" ss:Weight="1"/><Border ss:LineStyle="Continuous" ss:Position="Right" ss:Weight="1"/><Border ss:LineStyle="Continuous" ss:Position="Top" ss:Weight="1"/></Borders><Font ss:Size="8.0"/></Style><Style ss:ID="s51"><Alignment ss:Horizontal="Left" ss:Vertical="Top" ss:WrapText="1"/><Borders><Border ss:LineStyle="Continuous" ss:Position="Bottom" ss:Weight="1"/><Border ss:LineStyle="Continuous" ss:Position="Left" ss:Weight="1"/><Border ss:LineStyle="Continuous" ss:Position="Right" ss:Weight="1"/><Border ss:LineStyle="Continuous" ss:Position="Top" ss:Weight="1"/></Borders><Font ss:Color="#0000FF" ss:Size="8.0"/></Style><Style ss:ID="s52"><Alignment ss:Horizontal="Left" ss:Vertical="Top" ss:WrapText="1"/><Borders><Border ss:LineStyle="Continuous" ss:Position="Bottom" ss:Weight="1"/><Border ss:LineStyle="Continuous" ss:Position="Left" ss:Weight="1"/><Border ss:LineStyle="Continuous" ss:Position="Right" ss:Weight="1"/><Border ss:LineStyle="Continuous" ss:Position="Top" ss:Weight="1"/></Borders><Font ss:Color="#008080" ss:Size="8.0"/></Style></Styles><Worksheet ss:Name="Matching Table"><Table ss:DefaultColumnWidth="100.0" ss:DefaultRowHeight="10.0" ss:StyleID="s0" x:FullColumns="1" x:FullRows="1"><Column ss:AutoFitWidth="0" ss:StyleID="s0" ss:Width="100.0"/><Column ss:AutoFitWidth="0" ss:StyleID="s0" ss:Width="100.0"/><Column ss:AutoFitWidth="0" ss:StyleID="s0" ss:Width="100.0"/><Column ss:AutoFitWidth="0" ss:StyleID="s0" ss:Width="100.0"/><Column ss:AutoFitWidth="0" ss:StyleID="s0" ss:Width="100.0"/><Column ss:AutoFitWidth="0" ss:StyleID="s0" ss:Width="100.0"/><Column ss:AutoFitWidth="0" ss:StyleID="s0" ss:Width="100.0"/><Column ss:AutoFitWidth="0" ss:StyleID="s1" ss:Width="12.0"/><Column ss:AutoFitWidth="0" ss:StyleID="s0" ss:Width="100.0"/><Column ss:AutoFitWidth="0" ss:StyleID="s0" ss:Width="100.0"/><Column ss:AutoFitWidth="0" ss:StyleID="s0" ss:Width="100.0"/><Column ss:AutoFitWidth="0" ss:StyleID="s0" ss:Width="100.0"/><Column ss:AutoFitWidth="0" ss:StyleID="s0" ss:Width="100.0"/><Column ss:AutoFitWidth="0" ss:StyleID="s0" ss:Width="100.0"/><Column ss:AutoFitWidth="0" ss:StyleID="s0" ss:Width="100.0"/><Column ss:AutoFitWidth="0" ss:StyleID="s0" ss:Width="100.0"/><Column ss:AutoFitWidth="0" ss:StyleID="s0" ss:Width="100.0"/><Row ss:AutoFitHeight="0" ss:Height="19.0"><Cell ss:MergeAcross="6" ss:StyleID="s2"><Data ss:Type="String">Application Schema 'Activity Complex' (version 3.0)</Data></Cell><Cell ss:StyleID="s1"/><Cell ss:MergeAcross="8" ss:StyleID="s2"><Data ss:Type="String">Application Schema &lt;provide name of source schema&gt;</Data></Cell></Row><Row ss:AutoFitHeight="1" ss:Height="40.0"><Cell ss:StyleID="s3"><Data ss:Type="String">Type</Data></Cell><Cell ss:StyleID="s3"><Data ss:Type="String">Documentation</Data></Cell><Cell ss:StyleID="s3"><Data ss:Type="String"><B xmlns="http://www.w3.org/TR/REC-html40">Attribute&#13;<Font html:Color="#0000FF">Association role&#13;</Font><Font html:Color="#008080">Constraint</Font></B></Data></Cell><Cell ss:StyleID="s3"><Data ss:Type="String"><B xmlns="http://www.w3.org/TR/REC-html40">Attribute / <Font html:Color="#0000FF">Association role</Font> / <Font html:Color="#008080">Constraint</Font> documentation</B></Data></Cell><Cell ss:StyleID="s3"><Data ss:Type="String">Values / Enumerations</Data></Cell><Cell ss:StyleID="s3"><Data ss:Type="String">Multiplicity</Data></Cell><Cell ss:StyleID="s3"><Data ss:Type="String">Voidable / Non-Voidable</Data></Cell><Cell ss:StyleID="s1"/><Cell ss:StyleID="s3"><Data ss:Type="String">Type</Data></Cell><Cell ss:StyleID="s3"><Data ss:Type="String">Documentation</Data></Cell><Cell ss:StyleID="s3"><Data ss:Type="String"><B xmlns="http://www.w3.org/TR/REC-html40">Attribute&#13;<Font html:Color="#0000FF">Association role&#13;</Font><Font html:Color="#008080">Constraint</Font></B></Data></Cell><Cell ss:StyleID="s3"><Data ss:Type="String"><B xmlns="http://www.w3.org/TR/REC-html40">Attribute / <Font html:Color="#0000FF">Association role</Font> / <Font html:Color="#008080">Constraint</Font> documentation</B></Data></Cell><Cell ss:StyleID="s3"><Data ss:Type="String">Values / Enumerations</Data></Cell><Cell ss:StyleID="s3"><Data ss:Type="String">Multiplicity</Data></Cell><Cell ss:StyleID="s3"><Data ss:Type="String">Voidable / Non-Voidable</Data></Cell><Cell ss:StyleID="s3"><Data ss:Type="String">Status</Data></Cell><Cell ss:StyleID="s3"><Data ss:Type="String">Remarks</Data></Cell></Row><Row ss:AutoFitHeight="1" ss:Height="20.0"><Cell ss:MergeDown="8" ss:StyleID="s4"><Data ss:Type="String"><B xmlns="http://www.w3.org/TR/REC-html40">Permission</B></Data></Cell><Cell ss:MergeDown="8" ss:StyleID="s5"><Data ss:Type="String">-- Name --&#13;
permission&#13;
&#13;
&#13;
Official Decision (formal consent) granting authorization to operate all or part of an Activity Complex, subject to certain conditions which guarantee that the installations or parts of installations on the same site operated by the same operator comply with the requirements fixed by a competent authority. A permit may cover one or more functions and fix parameters of capacity. The term could be extended to other kind of certificates or documents of special relevance depending of the scope (e.g. ISO, EMAS, National Quality Standards, etc).&#13;
&#13;
The term may be extended to other kind of certificates or documents of special relevance depending of the scope (e.g. ISO, EMAS, National Quality Standards, etc).&#13;&#13;NOTE This terms is referred in several legislative acts as &amp;ldquo;permit&amp;rdquo; , &amp;ldquo;authorization&amp;rdquo;, &amp;ldquo;development consent&amp;rdquo; or &amp;ldquo;exploration permit&amp;rdquo; among others.&#13;
&#13;
EXAMPLE 1 &amp;ldquo;&amp;hellip;a [written] decision by which the competent authority grants permission to operate all or part of an installation&amp;rdquo; ;&#13;
EXAMPLE 2 &amp;ldquo;.. the decision of the competent authority or authorities which entitles the developer to proceed with the project..&amp;rdquo;.</Data></Cell><Cell ss:StyleID="s5"/><Cell ss:StyleID="s5"/><Cell ss:StyleID="s5"/><Cell ss:StyleID="s5"/><Cell ss:StyleID="s5"/><Cell ss:StyleID="s1"/><Cell ss:StyleID="s5"/><Cell ss:StyleID="s5"/><Cell ss:StyleID="s5"/><Cell ss:StyleID="s5"/><Cell ss:StyleID="s5"/><Cell ss:StyleID="s5"/><Cell ss:StyleID="s5"/><Cell ss:StyleID="s5"/><Cell ss:StyleID="s5"/></Row><Row ss:AutoFitHeight="1" ss:Height="18.0"><Cell ss:Index="3" ss:StyleID="s4"><Data ss:Type="String">Id</Data></Cell><Cell ss:StyleID="s5"><Data ss:Type="String">-- Name --&#13;
identifier&#13;
&#13;
&#13;
Identifying reference to the permission.</Data></Cell><Cell ss:StyleID="s5"><Data ss:Type="String">ThematicIdentifier&#13;</Data></Cell><Cell ss:StyleID="s5"><Data ss:Type="String">0..*</Data></Cell><Cell ss:StyleID="s5"/><Cell ss:StyleID="s1"/><Cell ss:StyleID="s5"/><Cell ss:StyleID="s5"/><Cell ss:StyleID="s5"/><Cell ss:StyleID="s5"/><Cell ss:StyleID="s5"/><Cell ss:StyleID="s5"/><Cell ss:StyleID="s5"/><Cell ss:StyleID="s5"/><Cell ss:StyleID="s5"/></Row><Row ss:AutoFitHeight="1" ss:Height="18.0"><Cell ss:Index="3" ss:StyleID="s4"><Data ss:Type="String">relatedParty</Data></Cell><Cell ss:StyleID="s5"><Data ss:Type="String">-- Name --&#13;
related party&#13;
&#13;
&#13;
Parties related to the permission granted to the activity complex open to many different roles, such as Competent Authorities or Company among others&#13;&#13;NOTE Include concepts described on the legislation such as Operator, Company, Port Authority, Agent, Holder, Competent Authority or Keeper.</Data></Cell><Cell ss:StyleID="s5"><Data ss:Type="String">RelatedParty&#13;</Data></Cell><Cell ss:StyleID="s5"><Data ss:Type="String">0..*</Data></Cell><Cell ss:StyleID="s5"><Data ss:Type="String">voidable</Data></Cell><Cell ss:StyleID="s1"/><Cell ss:StyleID="s5"/><Cell ss:StyleID="s5"/><Cell ss:StyleID="s5"/><Cell ss:StyleID="s5"/><Cell ss:StyleID="s5"/><Cell ss:StyleID="s5"/><Cell ss:StyleID="s5"/><Cell ss:StyleID="s5"/><Cell ss:StyleID="s5"/></Row><Row ss:AutoFitHeight="1" ss:Height="18.0"><Cell ss:Index="3" ss:StyleID="s4"><Data ss:Type="String">decisionDate</Data></Cell><Cell ss:StyleID="s5"><Data ss:Type="String">-- Name --&#13;
decision date&#13;
&#13;
&#13;
Temporal reference that complement the definition of the permission.&#13;&#13;NOTE For permissions that become effective immediately, the decision date and the start of the validity period coincide. It may however be a duration of years or decades that separates a decision date from the validity period. For example, a permission decided in 2012 may allow the recovery of waste at a particular site starting from the year&#13;
&#13;
EXAMPLE  Legal resolutions used to refer to a specific day from which the referred resolution and the emitted permission starts to be valid.</Data></Cell><Cell ss:StyleID="s5"><Data ss:Type="String">DateTime&#13;</Data></Cell><Cell ss:StyleID="s5"><Data ss:Type="String">1</Data></Cell><Cell ss:StyleID="s5"><Data ss:Type="String">voidable</Data></Cell><Cell ss:StyleID="s1"/><Cell ss:StyleID="s5"/><Cell ss:StyleID="s5"/><Cell ss:StyleID="s5"/><Cell ss:StyleID="s5"/><Cell ss:StyleID="s5"/><Cell ss:StyleID="s5"/><Cell ss:StyleID="s5"/><Cell ss:StyleID="s5"/><Cell ss:StyleID="s5"/></Row><Row ss:AutoFitHeight="1" ss:Height="18.0"><Cell ss:Index="3" ss:StyleID="s4"><Data ss:Type="String">dateFrom</Data></Cell><Cell ss:StyleID="s5"><Data ss:Type="String">-- Name --&#13;
date from&#13;
&#13;
&#13;
A date starting from which the permission applies and is valid.</Data></Cell><Cell ss:StyleID="s5"><Data ss:Type="String">DateTime&#13;</Data></Cell><Cell ss:StyleID="s5"><Data ss:Type="String">1</Data></Cell><Cell ss:StyleID="s5"><Data ss:Type="String">voidable</Data></Cell><Cell ss:StyleID="s1"/><Cell ss:StyleID="s5"/><Cell ss:StyleID="s5"/><Cell ss:StyleID="s5"/><Cell ss:StyleID="s5"/><Cell ss:StyleID="s5"/><Cell ss:StyleID="s5"/><Cell ss:StyleID="s5"/><Cell ss:StyleID="s5"/><Cell ss:StyleID="s5"/></Row><Row ss:AutoFitHeight="1" ss:Height="18.0"><Cell ss:Index="3" ss:StyleID="s4"><Data ss:Type="String">dateTo</Data></Cell><Cell ss:StyleID="s5"><Data ss:Type="String">-- Name --&#13;
date to&#13;
&#13;
&#13;
A date up to which the permission applies and is valid.</Data></Cell><Cell ss:StyleID="s5"><Data ss:Type="String">DateTime&#13;</Data></Cell><Cell ss:StyleID="s5"><Data ss:Type="String">0..1</Data></Cell><Cell ss:StyleID="s5"><Data ss:Type="String">voidable</Data></Cell><Cell ss:StyleID="s1"/><Cell ss:StyleID="s5"/><Cell ss:StyleID="s5"/><Cell ss:StyleID="s5"/><Cell ss:StyleID="s5"/><Cell ss:StyleID="s5"/><Cell ss:StyleID="s5"/><Cell ss:StyleID="s5"/><Cell ss:StyleID="s5"/><Cell ss:StyleID="s5"/></Row><Row ss:AutoFitHeight="1" ss:Height="18.0"><Cell ss:Index="3" ss:StyleID="s4"><Data ss:Type="String">description</Data></Cell><Cell ss:StyleID="s5"><Data ss:Type="String">-- Name --&#13;
description&#13;
&#13;
&#13;
A description of the permission.</Data></Cell><Cell ss:StyleID="s5"><Data ss:Type="String">PT_FreeText&#13;</Data></Cell><Cell ss:StyleID="s5"><Data ss:Type="String">0..1</Data></Cell><Cell ss:StyleID="s5"><Data ss:Type="String">voidable</Data></Cell><Cell ss:StyleID="s1"/><Cell ss:StyleID="s5"/><Cell ss:StyleID="s5"/><Cell ss:StyleID="s5"/><Cell ss:StyleID="s5"/><Cell ss:StyleID="s5"/><Cell ss:StyleID="s5"/><Cell ss:StyleID="s5"/><Cell ss:StyleID="s5"/><Cell ss:StyleID="s5"/></Row><Row ss:AutoFitHeight="1" ss:Height="18.0"><Cell ss:Index="3" ss:StyleID="s4"><Data ss:Type="String">permittedFunction</Data></Cell><Cell ss:StyleID="s5"><Data ss:Type="String">-- Name --&#13;
permitted function&#13;
&#13;
&#13;
Function/s for which the permission is granted. Function is as described by the Activity and potentially complemented by information about the Inputs and Outputs derived from the same.&#13;&#13;NOTE Functions permitted according to the permission, such as a permit for a landfill.</Data></Cell><Cell ss:StyleID="s5"><Data ss:Type="String">Function&#13;</Data></Cell><Cell ss:StyleID="s5"><Data ss:Type="String">0..*</Data></Cell><Cell ss:StyleID="s5"><Data ss:Type="String">voidable</Data></Cell><Cell ss:StyleID="s1"/><Cell ss:StyleID="s5"/><Cell ss:StyleID="s5"/><Cell ss:StyleID="s5"/><Cell ss:StyleID="s5"/><Cell ss:StyleID="s5"/><Cell ss:StyleID="s5"/><Cell ss:StyleID="s5"/><Cell ss:StyleID="s5"/><Cell ss:StyleID="s5"/></Row><Row ss:AutoFitHeight="1" ss:Height="18.0"><Cell ss:Index="3" ss:StyleID="s4"><Data ss:Type="String">permittedCapacity</Data></Cell><Cell ss:StyleID="s5"><Data ss:Type="String">-- Name --&#13;
permitted capacity&#13;
&#13;
&#13;
Maximum amounts of activity input and/or output according to the permission,&#13;&#13;NOTE The physical capacities of a facility may exceed the permitted capacities. &#13;
EXAMPLE Incineration of at most 100000 tons of residual waste per year.</Data></Cell><Cell ss:StyleID="s5"><Data ss:Type="String">Capacity&#13;</Data></Cell><Cell ss:StyleID="s5"><Data ss:Type="String">0..*</Data></Cell><Cell ss:StyleID="s5"><Data ss:Type="String">voidable</Data></Cell><Cell ss:StyleID="s1"/><Cell ss:StyleID="s5"/><Cell ss:StyleID="s5"/><Cell ss:StyleID="s5"/><Cell ss:StyleID="s5"/><Cell ss:StyleID="s5"/><Cell ss:StyleID="s5"/><Cell ss:StyleID="s5"/><Cell ss:StyleID="s5"/><Cell ss:StyleID="s5"/></Row><Row ss:Height="5.0"><Cell ss:StyleID="s3"/><Cell ss:StyleID="s3"/><Cell ss:StyleID="s3"/><Cell ss:StyleID="s3"/><Cell ss:StyleID="s3"/><Cell ss:StyleID="s3"/><Cell ss:StyleID="s3"/><Cell ss:StyleID="s1"/><Cell ss:StyleID="s3"/><Cell ss:StyleID="s3"/><Cell ss:StyleID="s3"/><Cell ss:StyleID="s3"/><Cell ss:StyleID="s3"/><Cell ss:StyleID="s3"/><Cell ss:StyleID="s3"/><Cell ss:StyleID="s3"/><Cell ss:StyleID="s3"/></Row><Row ss:AutoFitHeight="1" ss:Height="20.0"><Cell ss:MergeDown="5" ss:StyleID="s4"><Data ss:Type="String"><B xmlns="http://www.w3.org/TR/REC-html40">Capacity</B></Data></Cell><Cell ss:MergeDown="5" ss:StyleID="s5"><Data ss:Type="String">-- Name --&#13;
capacity&#13;
&#13;
&#13;
A quantification of an actual or potential ability to perform an activity, that typically does not change, does not change often, or does not change to a significant degree.&#13;&#13;NOTE  Capacity could refer depending of the thematic scope to different concepts included on the legislation as “emission limits”, “capacity incineration”, “livestock units”, “nominal capacity”, “objective estimation data”, “rate of desulphurization” or “recycling rate”.</Data></Cell><Cell ss:StyleID="s5"/><Cell ss:StyleID="s5"/><Cell ss:StyleID="s5"/><Cell ss:StyleID="s5"/><Cell ss:StyleID="s5"/><Cell ss:StyleID="s1"/><Cell ss:StyleID="s5"/><Cell ss:StyleID="s5"/><Cell ss:StyleID="s5"/><Cell ss:StyleID="s5"/><Cell ss:StyleID="s5"/><Cell ss:StyleID="s5"/><Cell ss:StyleID="s5"/><Cell ss:StyleID="s5"/><Cell ss:StyleID="s5"/></Row><Row ss:AutoFitHeight="1" ss:Height="18.0"><Cell ss:Index="3" ss:StyleID="s4"><Data ss:Type="String">activity</Data></Cell><Cell ss:StyleID="s5"><Data ss:Type="String">-- Name --&#13;
activity&#13;
&#13;
&#13;
Categorized description of individual or organized set of technically related processes that are carried out by a economical unit, private or public, profit or non profit character.&#13;&#13;NOTE The Activity described as part of the Function for &amp;ldquo;Activity Complex&amp;rdquo; should be recorded using a controlled vocabulary where a particular controlled vocabulary is in use within a given context, such as SIC codes in the UK, it is acceptable to use these, however, the preferred choice for European interoperability is whenever possible NACE [NACE].</Data></Cell><Cell ss:StyleID="s5"><Data ss:Type="String">EconomicActivityValue&#13;</Data></Cell><Cell ss:StyleID="s5"><Data ss:Type="String">1..*</Data></Cell><Cell ss:StyleID="s5"/><Cell ss:StyleID="s1"/><Cell ss:StyleID="s5"/><Cell ss:StyleID="s5"/><Cell ss:StyleID="s5"/><Cell ss:StyleID="s5"/><Cell ss:StyleID="s5"/><Cell ss:StyleID="s5"/><Cell ss:StyleID="s5"/><Cell ss:StyleID="s5"/><Cell ss:StyleID="s5"/></Row><Row ss:AutoFitHeight="1" ss:Height="18.0"><Cell ss:Index="3" ss:StyleID="s4"><Data ss:Type="String">input</Data></Cell><Cell ss:StyleID="s5"><Data ss:Type="String">-- Name --&#13;
input&#13;
&#13;
&#13;
Measurable  information about parameters related with the inputs related with the activity carried out by the Activity Complex.&#13;&#13;NOTE  Depending on the thematic scope it can contain different values including terms as Registered Pollutants, Waste, Processed Products, leakage, etc.</Data></Cell><Cell ss:StyleID="s5"><Data ss:Type="String">InputOutputAmount&#13;</Data></Cell><Cell ss:StyleID="s5"><Data ss:Type="String">0..*</Data></Cell><Cell ss:StyleID="s5"/><Cell ss:StyleID="s1"/><Cell ss:StyleID="s5"/><Cell ss:StyleID="s5"/><Cell ss:StyleID="s5"/><Cell ss:StyleID="s5"/><Cell ss:StyleID="s5"/><Cell ss:StyleID="s5"/><Cell ss:StyleID="s5"/><Cell ss:StyleID="s5"/><Cell ss:StyleID="s5"/></Row><Row ss:AutoFitHeight="1" ss:Height="18.0"><Cell ss:Index="3" ss:StyleID="s4"><Data ss:Type="String">output</Data></Cell><Cell ss:StyleID="s5"><Data ss:Type="String">-- Name --&#13;
output&#13;
&#13;
&#13;
Measurable information about parameters related with the outputs derived from the activity carried out by the &amp;ldquo;Activity Complex&amp;rdquo;.&#13;&#13;NOTE  Depending on the thematic scope it can contain different values including terms as Registered Pollutants, Waste, Processed Products, leakage, etc.</Data></Cell><Cell ss:StyleID="s5"><Data ss:Type="String">InputOutputAmount&#13;</Data></Cell><Cell ss:StyleID="s5"><Data ss:Type="String">0..*</Data></Cell><Cell ss:StyleID="s5"/><Cell ss:StyleID="s1"/><Cell ss:StyleID="s5"/><Cell ss:StyleID="s5"/><Cell ss:StyleID="s5"/><Cell ss:StyleID="s5"/><Cell ss:StyleID="s5"/><Cell ss:StyleID="s5"/><Cell ss:StyleID="s5"/><Cell ss:StyleID="s5"/><Cell ss:StyleID="s5"/></Row><Row ss:AutoFitHeight="1" ss:Height="18.0"><Cell ss:Index="3" ss:StyleID="s4"><Data ss:Type="String">time</Data></Cell><Cell ss:StyleID="s5"><Data ss:Type="String">-- Name --&#13;
time&#13;
&#13;
&#13;
The duration of time to which the specified capacity refers, such as 1 year for an annual capacity.&#13;&#13;NOTE Total capacities are specified without duration of time.</Data></Cell><Cell ss:StyleID="s5"><Data ss:Type="String">Time&#13;</Data></Cell><Cell ss:StyleID="s5"><Data ss:Type="String">0..1</Data></Cell><Cell ss:StyleID="s5"/><Cell ss:StyleID="s1"/><Cell ss:StyleID="s5"/><Cell ss:StyleID="s5"/><Cell ss:StyleID="s5"/><Cell ss:StyleID="s5"/><Cell ss:StyleID="s5"/><Cell ss:StyleID="s5"/><Cell ss:StyleID="s5"/><Cell ss:StyleID="s5"/><Cell ss:StyleID="s5"/></Row><Row ss:AutoFitHeight="1" ss:Height="18.0"><Cell ss:Index="3" ss:StyleID="s4"><Data ss:Type="String">description</Data></Cell><Cell ss:StyleID="s5"><Data ss:Type="String">-- Name --&#13;
description&#13;
&#13;
&#13;
A description of the capacity.</Data></Cell><Cell ss:StyleID="s5"><Data ss:Type="String">PT_FreeText&#13;</Data></Cell><Cell ss:StyleID="s5"><Data ss:Type="String">0..1</Data></Cell><Cell ss:StyleID="s5"><Data ss:Type="String">voidable</Data></Cell><Cell ss:StyleID="s1"/><Cell ss:StyleID="s5"/><Cell ss:StyleID="s5"/><Cell ss:StyleID="s5"/><Cell ss:StyleID="s5"/><Cell ss:StyleID="s5"/><Cell ss:StyleID="s5"/><Cell ss:StyleID="s5"/><Cell ss:StyleID="s5"/><Cell ss:StyleID="s5"/></Row><Row ss:Height="5.0"><Cell ss:StyleID="s3"/><Cell ss:StyleID="s3"/><Cell ss:StyleID="s3"/><Cell ss:StyleID="s3"/><Cell ss:StyleID="s3"/><Cell ss:StyleID="s3"/><Cell ss:StyleID="s3"/><Cell ss:StyleID="s1"/><Cell ss:StyleID="s3"/><Cell ss:StyleID="s3"/><Cell ss:StyleID="s3"/><Cell ss:StyleID="s3"/><Cell ss:StyleID="s3"/><Cell ss:StyleID="s3"/><Cell ss:StyleID="s3"/><Cell ss:StyleID="s3"/><Cell ss:StyleID="s3"/></Row><Row ss:AutoFitHeight="1" ss:Height="20.0"><Cell ss:MergeDown="9" ss:StyleID="s4"><Data ss:Type="String"><B xmlns="http://www.w3.org/TR/REC-html40">ActivityComplex</B></Data></Cell><Cell ss:MergeDown="9" ss:StyleID="s5"><Data ss:Type="String">-- Name --&#13;
activity complex&#13;
&#13;
&#13;
A "single unit", both technically and economically, under the management control of the same legal entity (operator), covering activities as those listed in the Eurostat NACE classification, products and services. Activity Complex includes all infrastructure, equipment and materials. It must represent the whole area, at the same or different geographical location, managed by a "single unit".&#13;&#13;NOTE 1 This class describes the minimal set of elements necessary to describe and identify geographically a legal entity and the activities taken place on it under the context of a Environmental purposes.&#13;
&#13;
&#13;&#13;NOTE 2 "Activity Complex" could be assimilated to terms described on the legislation as Facility, Establishment, Plant, Holding, Organization ,Farm, Extractive Industries or Aquaculture Production Business among others&#13;
&#13;
EXAMPLE i.e. an Agro-business that is legally registered under the Emissions Directive.</Data></Cell><Cell ss:StyleID="s5"/><Cell ss:StyleID="s5"/><Cell ss:StyleID="s5"/><Cell ss:StyleID="s5"/><Cell ss:StyleID="s5"/><Cell ss:StyleID="s1"/><Cell ss:StyleID="s5"/><Cell ss:StyleID="s5"/><Cell ss:StyleID="s5"/><Cell ss:StyleID="s5"/><Cell ss:StyleID="s5"/><Cell ss:StyleID="s5"/><Cell ss:StyleID="s5"/><Cell ss:StyleID="s5"/><Cell ss:StyleID="s5"/></Row><Row ss:AutoFitHeight="1" ss:Height="18.0"><Cell ss:Index="3" ss:StyleID="s4"><Data ss:Type="String">inspireId</Data></Cell><Cell ss:StyleID="s5"><Data ss:Type="String">-- Name --&#13;
INSPIRE identifier&#13;
&#13;
&#13;
External object identifier of the “Activity Complex”.&#13;&#13;NOTE  An external object identifier is a unique object identifier published by the responsible body, which may be used by external applications to reference the spatial object. The identifier is an identifier of the spatial object, not an identifier of the real-world phenomenon.</Data></Cell><Cell ss:StyleID="s5"><Data ss:Type="String">Identifier&#13;</Data></Cell><Cell ss:StyleID="s5"><Data ss:Type="String">1</Data></Cell><Cell ss:StyleID="s5"/><Cell ss:StyleID="s1"/><Cell ss:StyleID="s5"/><Cell ss:StyleID="s5"/><Cell ss:StyleID="s5"/><Cell ss:StyleID="s5"/><Cell ss:StyleID="s5"/><Cell ss:StyleID="s5"/><Cell ss:StyleID="s5"/><Cell ss:StyleID="s5"/><Cell ss:StyleID="s5"/></Row><Row ss:AutoFitHeight="1" ss:Height="18.0"><Cell ss:Index="3" ss:StyleID="s4"><Data ss:Type="String">thematicId</Data></Cell><Cell ss:StyleID="s5"><Data ss:Type="String">-- Name --&#13;
thematic identifier&#13;
&#13;
&#13;
Thematic Activity Complex identifier.&#13;&#13;NOTE  It may be the identification code provided or maintained by the Member States public authority to identify the object in the context of specific or general thematic scopes. &#13;
&#13;
EXAMPLE  Assigned National PRTR Code.</Data></Cell><Cell ss:StyleID="s5"><Data ss:Type="String">ThematicIdentifier&#13;</Data></Cell><Cell ss:StyleID="s5"><Data ss:Type="String">0..*</Data></Cell><Cell ss:StyleID="s5"/><Cell ss:StyleID="s1"/><Cell ss:StyleID="s5"/><Cell ss:StyleID="s5"/><Cell ss:StyleID="s5"/><Cell ss:StyleID="s5"/><Cell ss:StyleID="s5"/><Cell ss:StyleID="s5"/><Cell ss:StyleID="s5"/><Cell ss:StyleID="s5"/><Cell ss:StyleID="s5"/></Row><Row ss:AutoFitHeight="1" ss:Height="18.0"><Cell ss:Index="3" ss:StyleID="s4"><Data ss:Type="String">name</Data></Cell><Cell ss:StyleID="s5"><Data ss:Type="String">-- Name --&#13;
name&#13;
&#13;
&#13;
Descriptive name of the &amp;ldquo;Activity Complex&amp;rdquo;.&#13;&#13;NOTE 1 Several names in different languages may be expressed.&#13;
&#13;
&#13;&#13;NOTE 2 It is recommended that the language of the name (part of the Geographical/Name data type) be filled whenever possible.</Data></Cell><Cell ss:StyleID="s5"><Data ss:Type="String">CharacterString&#13;</Data></Cell><Cell ss:StyleID="s5"><Data ss:Type="String">0..1</Data></Cell><Cell ss:StyleID="s5"><Data ss:Type="String">voidable</Data></Cell><Cell ss:StyleID="s1"/><Cell ss:StyleID="s5"/><Cell ss:StyleID="s5"/><Cell ss:StyleID="s5"/><Cell ss:StyleID="s5"/><Cell ss:StyleID="s5"/><Cell ss:StyleID="s5"/><Cell ss:StyleID="s5"/><Cell ss:StyleID="s5"/><Cell ss:StyleID="s5"/></Row><Row ss:AutoFitHeight="1" ss:Height="18.0"><Cell ss:Index="3" ss:StyleID="s4"><Data ss:Type="String">geometry</Data></Cell><Cell ss:StyleID="s5"><Data ss:Type="String">-- Name --&#13;
geometry&#13;
&#13;
&#13;
The geometry used to define the extent or position of the “Activity Complex”.&#13;&#13;NOTE 1 Based on the provided description, different geometries could be used to represent the Activity Complex as a one legal whole.&#13;
EXAMPLE  1 E-prtr geometry is given by a single point based on Geographical Coordinates (see below). In other levels of detail or depending on the Data Provider this could be represented [e.g.] by a Multi-poligon.&#13;
&#13;
EXAMPLE 2 PRTR - Legal act example: “ … the latitude and longitude coordinates within an arc of 5 minutes that avoid the direct identification of an individual holding….”.</Data></Cell><Cell ss:StyleID="s5"><Data ss:Type="String">GM_Object&#13;</Data></Cell><Cell ss:StyleID="s5"><Data ss:Type="String">1</Data></Cell><Cell ss:StyleID="s5"/><Cell ss:StyleID="s1"/><Cell ss:StyleID="s5"/><Cell ss:StyleID="s5"/><Cell ss:StyleID="s5"/><Cell ss:StyleID="s5"/><Cell ss:StyleID="s5"/><Cell ss:StyleID="s5"/><Cell ss:StyleID="s5"/><Cell ss:StyleID="s5"/><Cell ss:StyleID="s5"/></Row><Row ss:AutoFitHeight="1" ss:Height="18.0"><Cell ss:Index="3" ss:StyleID="s4"><Data ss:Type="String">function</Data></Cell><Cell ss:StyleID="s5"><Data ss:Type="String">-- Name --&#13;
function&#13;
&#13;
&#13;
&#13;
Activities performed by the activity complex. Function is described by the activity and potentially complemented with information about inputs and outputs as result of it.&#13;&#13;NOTE  The Activity described as part of the Function &amp;ldquo;Activity Complex&amp;rdquo; should be recorded using a controlled vocabulary where a particular controlled vocabulary is in use within a given context, such as SIC codes in the UK, it is acceptable to use these, however, the preferred choice for European interoperability is whenever possible NACE [NACE].</Data></Cell><Cell ss:StyleID="s5"><Data ss:Type="String">Function&#13;</Data></Cell><Cell ss:StyleID="s5"><Data ss:Type="String">1..*</Data></Cell><Cell ss:StyleID="s5"/><Cell ss:StyleID="s1"/><Cell ss:StyleID="s5"/><Cell ss:StyleID="s5"/><Cell ss:StyleID="s5"/><Cell ss:StyleID="s5"/><Cell ss:StyleID="s5"/><Cell ss:StyleID="s5"/><Cell ss:StyleID="s5"/><Cell ss:StyleID="s5"/><Cell ss:StyleID="s5"/></Row><Row ss:AutoFitHeight="1" ss:Height="18.0"><Cell ss:Index="3" ss:StyleID="s4"><Data ss:Type="String">validFrom</Data></Cell><Cell ss:StyleID="s5"><Data ss:Type="String">-- Name --&#13;
valid from&#13;
&#13;
&#13;
The time when the activity complex started to exist in the real world.</Data></Cell><Cell ss:StyleID="s5"><Data ss:Type="String">DateTime&#13;</Data></Cell><Cell ss:StyleID="s5"><Data ss:Type="String">1</Data></Cell><Cell ss:StyleID="s5"><Data ss:Type="String">voidable</Data></Cell><Cell ss:StyleID="s1"/><Cell ss:StyleID="s5"/><Cell ss:StyleID="s5"/><Cell ss:StyleID="s5"/><Cell ss:StyleID="s5"/><Cell ss:StyleID="s5"/><Cell ss:StyleID="s5"/><Cell ss:StyleID="s5"/><Cell ss:StyleID="s5"/><Cell ss:StyleID="s5"/></Row><Row ss:AutoFitHeight="1" ss:Height="18.0"><Cell ss:Index="3" ss:StyleID="s4"><Data ss:Type="String">validTo</Data></Cell><Cell ss:StyleID="s5"><Data ss:Type="String">-- Name --&#13;
valid to&#13;
&#13;
&#13;
The time when the activity complex no longer exists in the real world.</Data></Cell><Cell ss:StyleID="s5"><Data ss:Type="String">DateTime&#13;</Data></Cell><Cell ss:StyleID="s5"><Data ss:Type="String">0..1</Data></Cell><Cell ss:StyleID="s5"><Data ss:Type="String">voidable</Data></Cell><Cell ss:StyleID="s1"/><Cell ss:StyleID="s5"/><Cell ss:StyleID="s5"/><Cell ss:StyleID="s5"/><Cell ss:StyleID="s5"/><Cell ss:StyleID="s5"/><Cell ss:StyleID="s5"/><Cell ss:StyleID="s5"/><Cell ss:StyleID="s5"/><Cell ss:StyleID="s5"/></Row><Row ss:AutoFitHeight="1" ss:Height="18.0"><Cell ss:Index="3" ss:StyleID="s4"><Data ss:Type="String">beginLifespanVersion</Data></Cell><Cell ss:StyleID="s5"><Data ss:Type="String">-- Name --&#13;
begin lifespan version&#13;
&#13;
&#13;
Date and time at which this version of the spatial object was inserted or changed in the spatial data set.&#13;&#13;NOTE This date is recorded to enable the generation of change only update files.</Data></Cell><Cell ss:StyleID="s5"><Data ss:Type="String">DateTime&#13;</Data></Cell><Cell ss:StyleID="s5"><Data ss:Type="String">1</Data></Cell><Cell ss:StyleID="s5"><Data ss:Type="String">voidable</Data></Cell><Cell ss:StyleID="s1"/><Cell ss:StyleID="s5"/><Cell ss:StyleID="s5"/><Cell ss:StyleID="s5"/><Cell ss:StyleID="s5"/><Cell ss:StyleID="s5"/><Cell ss:StyleID="s5"/><Cell ss:StyleID="s5"/><Cell ss:StyleID="s5"/><Cell ss:StyleID="s5"/></Row><Row ss:AutoFitHeight="1" ss:Height="18.0"><Cell ss:Index="3" ss:StyleID="s4"><Data ss:Type="String">endLifespanVersion</Data></Cell><Cell ss:StyleID="s5"><Data ss:Type="String">-- Name --&#13;
end lifespan version&#13;
&#13;
&#13;
Date and time at which this version of the spatial object was superseded or retired in the spatial data set.&#13;&#13;NOTE This date is recorded primarily for those systems which "close" an entry in the spatial data set in the event of an attribute change.</Data></Cell><Cell ss:StyleID="s5"><Data ss:Type="String">DateTime&#13;</Data></Cell><Cell ss:StyleID="s5"><Data ss:Type="String">0..1</Data></Cell><Cell ss:StyleID="s5"><Data ss:Type="String">voidable</Data></Cell><Cell ss:StyleID="s1"/><Cell ss:StyleID="s5"/><Cell ss:StyleID="s5"/><Cell ss:StyleID="s5"/><Cell ss:StyleID="s5"/><Cell ss:StyleID="s5"/><Cell ss:StyleID="s5"/><Cell ss:StyleID="s5"/><Cell ss:StyleID="s5"/><Cell ss:StyleID="s5"/></Row><Row ss:Height="5.0"><Cell ss:StyleID="s3"/><Cell ss:StyleID="s3"/><Cell ss:StyleID="s3"/><Cell ss:StyleID="s3"/><Cell ss:StyleID="s3"/><Cell ss:StyleID="s3"/><Cell ss:StyleID="s3"/><Cell ss:StyleID="s1"/><Cell ss:StyleID="s3"/><Cell ss:StyleID="s3"/><Cell ss:StyleID="s3"/><Cell ss:StyleID="s3"/><Cell ss:StyleID="s3"/><Cell ss:StyleID="s3"/><Cell ss:StyleID="s3"/><Cell ss:StyleID="s3"/><Cell ss:StyleID="s3"/></Row><Row ss:AutoFitHeight="1" ss:Height="20.0"><Cell ss:MergeDown="4" ss:StyleID="s4"><Data ss:Type="String"><B xmlns="http://www.w3.org/TR/REC-html40">ActivityComplexDescription</B></Data></Cell><Cell ss:MergeDown="4" ss:StyleID="s5"><Data ss:Type="String">-- Name --&#13;
activity complex description&#13;
&#13;
&#13;
Additional information about an activity complex, including its description, address, contact and related parties.</Data></Cell><Cell ss:StyleID="s5"/><Cell ss:StyleID="s5"/><Cell ss:StyleID="s5"/><Cell ss:StyleID="s5"/><Cell ss:StyleID="s5"/><Cell ss:StyleID="s1"/><Cell ss:StyleID="s5"/><Cell ss:StyleID="s5"/><Cell ss:StyleID="s5"/><Cell ss:StyleID="s5"/><Cell ss:StyleID="s5"/><Cell ss:StyleID="s5"/><Cell ss:StyleID="s5"/><Cell ss:StyleID="s5"/><Cell ss:StyleID="s5"/></Row><Row ss:AutoFitHeight="1" ss:Height="18.0"><Cell ss:Index="3" ss:StyleID="s4"><Data ss:Type="String">description</Data></Cell><Cell ss:StyleID="s5"><Data ss:Type="String">-- Name --&#13;
description&#13;
&#13;
&#13;
A complementary definition of the “Activity Complex” and its characteristics.&#13;&#13;NOTE  Free text to include or refer any complementary information about the Activity Complex or its characteristics.</Data></Cell><Cell ss:StyleID="s5"><Data ss:Type="String">PT_FreeText&#13;</Data></Cell><Cell ss:StyleID="s5"><Data ss:Type="String">0..1</Data></Cell><Cell ss:StyleID="s5"><Data ss:Type="String">voidable</Data></Cell><Cell ss:StyleID="s1"/><Cell ss:StyleID="s5"/><Cell ss:StyleID="s5"/><Cell ss:StyleID="s5"/><Cell ss:StyleID="s5"/><Cell ss:StyleID="s5"/><Cell ss:StyleID="s5"/><Cell ss:StyleID="s5"/><Cell ss:StyleID="s5"/><Cell ss:StyleID="s5"/></Row><Row ss:AutoFitHeight="1" ss:Height="18.0"><Cell ss:Index="3" ss:StyleID="s4"><Data ss:Type="String">address</Data></Cell><Cell ss:StyleID="s5"><Data ss:Type="String">-- Name --&#13;
address&#13;
&#13;
&#13;
An address for the activity complex, i.e., an address where the activities occur.</Data></Cell><Cell ss:StyleID="s5"><Data ss:Type="String">AddressRepresentation&#13;</Data></Cell><Cell ss:StyleID="s5"><Data ss:Type="String">0..1</Data></Cell><Cell ss:StyleID="s5"><Data ss:Type="String">voidable</Data></Cell><Cell ss:StyleID="s1"/><Cell ss:StyleID="s5"/><Cell ss:StyleID="s5"/><Cell ss:StyleID="s5"/><Cell ss:StyleID="s5"/><Cell ss:StyleID="s5"/><Cell ss:StyleID="s5"/><Cell ss:StyleID="s5"/><Cell ss:StyleID="s5"/><Cell ss:StyleID="s5"/></Row><Row ss:AutoFitHeight="1" ss:Height="18.0"><Cell ss:Index="3" ss:StyleID="s4"><Data ss:Type="String">contact</Data></Cell><Cell ss:StyleID="s5"><Data ss:Type="String">-- Name --&#13;
contact&#13;
&#13;
&#13;
Contact information for the activity complex.</Data></Cell><Cell ss:StyleID="s5"><Data ss:Type="String">Contact&#13;</Data></Cell><Cell ss:StyleID="s5"><Data ss:Type="String">0..1</Data></Cell><Cell ss:StyleID="s5"><Data ss:Type="String">voidable</Data></Cell><Cell ss:StyleID="s1"/><Cell ss:StyleID="s5"/><Cell ss:StyleID="s5"/><Cell ss:StyleID="s5"/><Cell ss:StyleID="s5"/><Cell ss:StyleID="s5"/><Cell ss:StyleID="s5"/><Cell ss:StyleID="s5"/><Cell ss:StyleID="s5"/><Cell ss:StyleID="s5"/></Row><Row ss:AutoFitHeight="1" ss:Height="18.0"><Cell ss:Index="3" ss:StyleID="s4"><Data ss:Type="String">relatedParty</Data></Cell><Cell ss:StyleID="s5"><Data ss:Type="String">-- Name --&#13;
related party&#13;
&#13;
&#13;
Information on Parties related to the Activity Complex. It is open to many different roles, such as owners, operators or Competent Authorities.&#13;&#13;NOTE 1 The term covers concepts described on the legislation such as Operator, Company, Port Authority, Agent, Holder, Collector, Producer, Competent Authority or Keeper.</Data></Cell><Cell ss:StyleID="s5"><Data ss:Type="String">RelatedParty&#13;</Data></Cell><Cell ss:StyleID="s5"><Data ss:Type="String">0..*</Data></Cell><Cell ss:StyleID="s5"><Data ss:Type="String">voidable</Data></Cell><Cell ss:StyleID="s1"/><Cell ss:StyleID="s5"/><Cell ss:StyleID="s5"/><Cell ss:StyleID="s5"/><Cell ss:StyleID="s5"/><Cell ss:StyleID="s5"/><Cell ss:StyleID="s5"/><Cell ss:StyleID="s5"/><Cell ss:StyleID="s5"/><Cell ss:StyleID="s5"/></Row><Row ss:Height="5.0"><Cell ss:StyleID="s3"/><Cell ss:StyleID="s3"/><Cell ss:StyleID="s3"/><Cell ss:StyleID="s3"/><Cell ss:StyleID="s3"/><Cell ss:StyleID="s3"/><Cell ss:StyleID="s3"/><Cell ss:StyleID="s1"/><Cell ss:StyleID="s3"/><Cell ss:StyleID="s3"/><Cell ss:StyleID="s3"/><Cell ss:StyleID="s3"/><Cell ss:StyleID="s3"/><Cell ss:StyleID="s3"/><Cell ss:StyleID="s3"/><Cell ss:StyleID="s3"/><Cell ss:StyleID="s3"/></Row><Row ss:AutoFitHeight="1" ss:Height="20.0"><Cell ss:MergeDown="2" ss:StyleID="s4"><Data ss:Type="String"><B xmlns="http://www.w3.org/TR/REC-html40">InputOutputAmount</B></Data></Cell><Cell ss:MergeDown="2" ss:StyleID="s5"><Data ss:Type="String">-- Name --&#13;
amount of input or output&#13;
&#13;
&#13;
Type and, where available, measurable amount of a classified or registered material that enters or leaves a technical and economical unit.&#13;&#13;NOTE Depending on the thematic scope it can refer to different terms as Biomass, Bio-Waste, Fuel, Organic Solvents, Waste Water, Waste for disposal or recovery, Primary Materials, etc.</Data></Cell><Cell ss:StyleID="s5"/><Cell ss:StyleID="s5"/><Cell ss:StyleID="s5"/><Cell ss:StyleID="s5"/><Cell ss:StyleID="s5"/><Cell ss:StyleID="s1"/><Cell ss:StyleID="s5"/><Cell ss:StyleID="s5"/><Cell ss:StyleID="s5"/><Cell ss:StyleID="s5"/><Cell ss:StyleID="s5"/><Cell ss:StyleID="s5"/><Cell ss:StyleID="s5"/><Cell ss:StyleID="s5"/><Cell ss:StyleID="s5"/></Row><Row ss:AutoFitHeight="1" ss:Height="18.0"><Cell ss:Index="3" ss:StyleID="s4"><Data ss:Type="String">inputOutput</Data></Cell><Cell ss:StyleID="s5"><Data ss:Type="String">-- Name --&#13;
input/output&#13;
&#13;
&#13;
A  classified or registered type of material or something immaterial, that enters a technical and economical unit according to its function.&#13;&#13;NOTE Depending on the thematic scope it can contain different values including terms as Biomass, Bio-Waste, Fuel, Organic Solvents, Waste Water, Waste for disposal or recovery, Primary Materials, etc.</Data></Cell><Cell ss:StyleID="s5"><Data ss:Type="String">InputOutputValue&#13;</Data></Cell><Cell ss:StyleID="s5"><Data ss:Type="String">1</Data></Cell><Cell ss:StyleID="s5"/><Cell ss:StyleID="s1"/><Cell ss:StyleID="s5"/><Cell ss:StyleID="s5"/><Cell ss:StyleID="s5"/><Cell ss:StyleID="s5"/><Cell ss:StyleID="s5"/><Cell ss:StyleID="s5"/><Cell ss:StyleID="s5"/><Cell ss:StyleID="s5"/><Cell ss:StyleID="s5"/></Row><Row ss:AutoFitHeight="1" ss:Height="18.0"><Cell ss:Index="3" ss:StyleID="s4"><Data ss:Type="String">amount</Data></Cell><Cell ss:StyleID="s5"><Data ss:Type="String">-- Name --&#13;
amount&#13;
&#13;
&#13;
The amount (such as a volume or mass) of the classified or registered material that enters or leaves a technical and economical unit.</Data></Cell><Cell ss:StyleID="s5"><Data ss:Type="String">Measure&#13;</Data></Cell><Cell ss:StyleID="s5"><Data ss:Type="String">1</Data></Cell><Cell ss:StyleID="s5"><Data ss:Type="String">voidable</Data></Cell><Cell ss:StyleID="s1"/><Cell ss:StyleID="s5"/><Cell ss:StyleID="s5"/><Cell ss:StyleID="s5"/><Cell ss:StyleID="s5"/><Cell ss:StyleID="s5"/><Cell ss:StyleID="s5"/><Cell ss:StyleID="s5"/><Cell ss:StyleID="s5"/><Cell ss:StyleID="s5"/></Row><Row ss:Height="5.0"><Cell ss:StyleID="s3"/><Cell ss:StyleID="s3"/><Cell ss:StyleID="s3"/><Cell ss:StyleID="s3"/><Cell ss:StyleID="s3"/><Cell ss:StyleID="s3"/><Cell ss:StyleID="s3"/><Cell ss:StyleID="s1"/><Cell ss:StyleID="s3"/><Cell ss:StyleID="s3"/><Cell ss:StyleID="s3"/><Cell ss:StyleID="s3"/><Cell ss:StyleID="s3"/><Cell ss:StyleID="s3"/><Cell ss:StyleID="s3"/><Cell ss:StyleID="s3"/><Cell ss:StyleID="s3"/></Row><Row ss:AutoFitHeight="1" ss:Height="20.0"><Cell ss:MergeDown="4" ss:StyleID="s4"><Data ss:Type="String"><B xmlns="http://www.w3.org/TR/REC-html40">Function</B></Data></Cell><Cell ss:MergeDown="4" ss:StyleID="s5"><Data ss:Type="String">-- Name --&#13;
function&#13;
&#13;
&#13;
The function of something expressed as an activity and optional input and/or output.&#13;&#13;NOTE  Depending on the scope it can refer to different activities (co-incineration, Collection, exploration, incineration, interim disposal, management, recycling, primary production, primary treatment, recovery , recycling, release, storage, use, waste management, etc) and Inputs and Outputs (sludge, substance, tailings, technical products, urban waste water, volatile organic compound, waste, WEEE from private households, etc).</Data></Cell><Cell ss:StyleID="s5"/><Cell ss:StyleID="s5"/><Cell ss:StyleID="s5"/><Cell ss:StyleID="s5"/><Cell ss:StyleID="s5"/><Cell ss:StyleID="s1"/><Cell ss:StyleID="s5"/><Cell ss:StyleID="s5"/><Cell ss:StyleID="s5"/><Cell ss:StyleID="s5"/><Cell ss:StyleID="s5"/><Cell ss:StyleID="s5"/><Cell ss:StyleID="s5"/><Cell ss:StyleID="s5"/><Cell ss:StyleID="s5"/></Row><Row ss:AutoFitHeight="1" ss:Height="18.0"><Cell ss:Index="3" ss:StyleID="s4"><Data ss:Type="String">activity</Data></Cell><Cell ss:StyleID="s5"><Data ss:Type="String">-- Name --&#13;
activity&#13;
&#13;
&#13;
Categorized description of individual or organized set of technically related processes that are carried out by a economical unit, private or public, profit or non profit character.&#13;&#13;NOTE  The Activity described as part of the Function for &amp;ldquo;Activity Complex&amp;rdquo; should be recorded using a controlled vocabulary where a particular controlled vocabulary is in use within a given context, such as SIC codes in the UK, it is acceptable to use these, however, the preferred choice for European interoperability is whenever possible NACE [NACE].</Data></Cell><Cell ss:StyleID="s5"><Data ss:Type="String">EconomicActivityValue&#13;</Data></Cell><Cell ss:StyleID="s5"><Data ss:Type="String">1..*</Data></Cell><Cell ss:StyleID="s5"/><Cell ss:StyleID="s1"/><Cell ss:StyleID="s5"/><Cell ss:StyleID="s5"/><Cell ss:StyleID="s5"/><Cell ss:StyleID="s5"/><Cell ss:StyleID="s5"/><Cell ss:StyleID="s5"/><Cell ss:StyleID="s5"/><Cell ss:StyleID="s5"/><Cell ss:StyleID="s5"/></Row><Row ss:AutoFitHeight="1" ss:Height="18.0"><Cell ss:Index="3" ss:StyleID="s4"><Data ss:Type="String">input</Data></Cell><Cell ss:StyleID="s5"><Data ss:Type="String">-- Name --&#13;
input&#13;
&#13;
&#13;
A  classified or registered type of material or something immaterial, that enters a technical and economical unit according to its function.&#13;&#13;NOTE  Depending on the thematic scope it can contain different values including terms as Biomass, Bio-Waste, Fuel, Organic Solvents, Waste Water, Waste for disposal or recovery, Primary Materials, ..</Data></Cell><Cell ss:StyleID="s5"><Data ss:Type="String">InputOutputValue&#13;</Data></Cell><Cell ss:StyleID="s5"><Data ss:Type="String">0..*</Data></Cell><Cell ss:StyleID="s5"><Data ss:Type="String">voidable</Data></Cell><Cell ss:StyleID="s1"/><Cell ss:StyleID="s5"/><Cell ss:StyleID="s5"/><Cell ss:StyleID="s5"/><Cell ss:StyleID="s5"/><Cell ss:StyleID="s5"/><Cell ss:StyleID="s5"/><Cell ss:StyleID="s5"/><Cell ss:StyleID="s5"/><Cell ss:StyleID="s5"/></Row><Row ss:AutoFitHeight="1" ss:Height="18.0"><Cell ss:Index="3" ss:StyleID="s4"><Data ss:Type="String">output</Data></Cell><Cell ss:StyleID="s5"><Data ss:Type="String">-- Name --&#13;
output&#13;
&#13;
&#13;
A  classified or registered type of material or something immaterial, that leaves a technical and economical unit according to its function, ".&#13;&#13;NOTE Depending on the thematic scope it can contain different values including terms as Registered Pollutants, Waste, Processed Products, leakage, etc.</Data></Cell><Cell ss:StyleID="s5"><Data ss:Type="String">InputOutputValue&#13;</Data></Cell><Cell ss:StyleID="s5"><Data ss:Type="String">0..*</Data></Cell><Cell ss:StyleID="s5"><Data ss:Type="String">voidable</Data></Cell><Cell ss:StyleID="s1"/><Cell ss:StyleID="s5"/><Cell ss:StyleID="s5"/><Cell ss:StyleID="s5"/><Cell ss:StyleID="s5"/><Cell ss:StyleID="s5"/><Cell ss:StyleID="s5"/><Cell ss:StyleID="s5"/><Cell ss:StyleID="s5"/><Cell ss:StyleID="s5"/></Row><Row ss:AutoFitHeight="1" ss:Height="18.0"><Cell ss:Index="3" ss:StyleID="s4"><Data ss:Type="String">description</Data></Cell><Cell ss:StyleID="s5"><Data ss:Type="String">-- Name --&#13;
description&#13;
&#13;
&#13;
A more detailed description of the function.</Data></Cell><Cell ss:StyleID="s5"><Data ss:Type="String">PT_FreeText&#13;</Data></Cell><Cell ss:StyleID="s5"><Data ss:Type="String">0..1</Data></Cell><Cell ss:StyleID="s5"><Data ss:Type="String">voidable</Data></Cell><Cell ss:StyleID="s1"/><Cell ss:StyleID="s5"/><Cell ss:StyleID="s5"/><Cell ss:StyleID="s5"/><Cell ss:StyleID="s5"/><Cell ss:StyleID="s5"/><Cell ss:StyleID="s5"/><Cell ss:StyleID="s5"/><Cell ss:StyleID="s5"/><Cell ss:StyleID="s5"/></Row><Row ss:Height="5.0"><Cell ss:StyleID="s3"/><Cell ss:StyleID="s3"/><Cell ss:StyleID="s3"/><Cell ss:StyleID="s3"/><Cell ss:StyleID="s3"/><Cell ss:StyleID="s3"/><Cell ss:StyleID="s3"/><Cell ss:StyleID="s1"/><Cell ss:StyleID="s3"/><Cell ss:StyleID="s3"/><Cell ss:StyleID="s3"/><Cell ss:StyleID="s3"/><Cell ss:StyleID="s3"/><Cell ss:StyleID="s3"/><Cell ss:StyleID="s3"/><Cell ss:StyleID="s3"/><Cell ss:StyleID="s3"/></Row></Table></Worksheet></Workbook>